{
  "trigger": {
    "type": "EVENT",
    "eventNames": ["service.expiring", "service.grace_start"]
  },
  "conditions": {
    "rules": [
      { "field": "balance_sufficient", "operator": "eq", "value": 0 }
    ]
  },
  "steps": [
    {
      "id": "grace_day1",
      "name": "Day 1",
      "templateKey": "vds_expiration",
      "offerVariantKey": "renew_discount",
      "delayHours": 0
    },
    {
      "id": "grace_day2",
      "name": "Day 2",
      "templateKey": "grace_day2",
      "offerVariantKey": "renew_discount",
      "delayHours": 24
    },
    {
      "id": "grace_day3",
      "name": "Day 3",
      "templateKey": "grace_day3",
      "offerVariantKey": "renew_discount",
      "delayHours": 48
    }
  ],
  "offers": {
    "renew_discount": {
      "key": "renew_discount",
      "type": "discount_percent",
      "scope": "renewal",
      "value": 5,
      "ttlHours": 72,
      "autoApply": true,
      "claimButton": false
    }
  },
  "templates": {
    "vds_expiration": {
      "key": "vds_expiration",
      "ru": { "text": "⏰ <strong>Срок VDS истёк</strong>\n\n💰 Пополните баланс на {{amount}} $.\n🎁 Скидка <b>5%</b> на продление — ещё <strong>72 ч</strong>." },
      "en": { "text": "⏰ <strong>VDS subscription expired</strong>\n\n💰 Top up {{amount}} $.\n🎁 <b>5%</b> renewal discount — <strong>72h</strong> left." }
    },
    "grace_day2": {
      "key": "grace_day2",
      "ru": { "text": "🎁 <strong>Напоминание о VDS</strong>\n\nСкидка <b>+5%</b> на продление — ещё <strong>24 часа</strong>.\n\nПродлите сейчас, чтобы сохранить данные." },
      "en": { "text": "🎁 <strong>VDS reminder</strong>\n\n<b>+5%</b> renewal discount — <strong>24 more hours</strong>.\n\nRenew now to keep your data." }
    },
    "grace_day3": {
      "key": "grace_day3",
      "ru": { "text": "🔴 <strong>Последний день</strong>\n\nVDS скоро будет удалена. Скидка <b>5%</b> на продление ещё активна.\n\nПродлите сейчас — данные сохранятся." },
      "en": { "text": "🔴 <strong>Last day</strong>\n\nVDS will be deleted soon. <b>5%</b> renewal discount still active.\n\nRenew now to save your data." }
    }
  },
  "throttle": { "perStepCap": 1 },
  "attribution": { "conversionWindowHours": 72, "successEvent": "renew", "model": "last_touch" }
}
